toughradius/__init__.py
toughradius/__init__.pyc
toughradius/settings.py
toughradius/common/__init__.py
toughradius/common/json_log_formater.py
toughradius/common/radclient.py
toughradius/common/radiusd.py
toughradius/common/radtest.py
toughradius/common/six.py
toughradius/common/tools.py
toughradius/dictionarys/dictionary
toughradius/dictionarys/dictionary.3com
toughradius/dictionarys/dictionary.3gpp
toughradius/dictionarys/dictionary.3gpp2
toughradius/dictionarys/dictionary.acc
toughradius/dictionarys/dictionary.acme
toughradius/dictionarys/dictionary.airespace
toughradius/dictionarys/dictionary.alcatel
toughradius/dictionarys/dictionary.alcatel.esam
toughradius/dictionarys/dictionary.alcatel.sr
toughradius/dictionarys/dictionary.alteon
toughradius/dictionarys/dictionary.altiga
toughradius/dictionarys/dictionary.alvarion
toughradius/dictionarys/dictionary.apc
toughradius/dictionarys/dictionary.aptis
toughradius/dictionarys/dictionary.aruba
toughradius/dictionarys/dictionary.ascend
toughradius/dictionarys/dictionary.asn
toughradius/dictionarys/dictionary.attingo
toughradius/dictionarys/dictionary.audiocodes
toughradius/dictionarys/dictionary.avaya
toughradius/dictionarys/dictionary.azaire
toughradius/dictionarys/dictionary.bay
toughradius/dictionarys/dictionary.bintec
toughradius/dictionarys/dictionary.bristol
toughradius/dictionarys/dictionary.cablelabs
toughradius/dictionarys/dictionary.cabletron
toughradius/dictionarys/dictionary.chillispot
toughradius/dictionarys/dictionary.cisco
toughradius/dictionarys/dictionary.cisco.bbsm
toughradius/dictionarys/dictionary.cisco.vpn3000
toughradius/dictionarys/dictionary.cisco.vpn5000
toughradius/dictionarys/dictionary.clavister
toughradius/dictionarys/dictionary.colubris
toughradius/dictionarys/dictionary.columbia_university
toughradius/dictionarys/dictionary.compat
toughradius/dictionarys/dictionary.coova
toughradius/dictionarys/dictionary.cosine
toughradius-5.0.0.6.dist-info/DESCRIPTION.rst
toughradius-5.0.0.6.dist-info/METADATA
toughradius-5.0.0.6.dist-info/RECORD
toughradius-5.0.0.6.dist-info/WHEEL
toughradius-5.0.0.6.dist-info/eager_resources.txt
toughradius-5.0.0.6.dist-info/entry_points.txt
toughradius-5.0.0.6.dist-info/metadata.json
toughradius-5.0.0.6.dist-info/top_level.txt
toughradius-5.0.0.6.dist-info/zip-safe
