Metadata-Version: 2.0
Name: toughradius
Version: 5.0.0.6
Summary: Beautiful open source RadiusServer
Home-page: https://github.com/talkincode/toughradius
Author: jamiesun
Author-email: jamiesun.net@gmail.com
License: Apache License 2.0
Keywords: radius,AAA,authentication,accounting,authorization,toughradius
Platform: UNKNOWN
Classifier: Development Status :: 6 - Mature
Classifier: Intended Audience :: Developers
Classifier: Programming Language :: Python :: 2.7
Classifier: Topic :: Software Development :: Libraries :: Python Modules
Classifier: Topic :: System :: Systems Administration :: Authentication/Directory
Requires-Dist: gevent (==1.1.2)
